rawtherapee_auto/__init__.py
rawtherapee_auto/cli.py
rawtherapee_auto/file_mover.py
rawtherapee_auto/monitor.py
rawtherapee_auto/processing.py
rawtherapee_auto/res/auto-correction.pp3
rawtherapee_auto-0.1.1.dist-info/LICENSE
rawtherapee_auto-0.1.1.dist-info/WHEEL
rawtherapee_auto-0.1.1.dist-info/entry_points.txt
rawtherapee_auto-0.1.1.dist-info/METADATA
rawtherapee_auto-0.1.1.dist-info/RECORD
