Metadata-Version: 2.1
Name: rawtherapee-auto
Version: 0.1.1
Summary: Import raw photos and use RawTherapee to auto-level them before copying them to an output location.
Home-page: https://github.com/Machione/rawtherapee-auto
License: GPL-3.0-only
Author: Ryan McKeown
Author-email: ryanmckeown@mail4me.com
Requires-Python: >=3.10,<4.0
Classifier: License :: OSI Approved :: GNU General Public License v3 (GPLv3)
Classifier: Programming Language :: Python :: 3
Classifier: Programming Language :: Python :: 3.10
Classifier: Programming Language :: Python :: 3.11
Requires-Dist: click (>=8.1.7,<9.0.0)
Requires-Dist: tqdm (>=4.66.5,<5.0.0)
Project-URL: Repository, https://github.com/Machione/rawtherapee-auto
